ardupilot_log_reader/__init__.py
ardupilot_log_reader/py.typed
ardupilot_log_reader/reader.py
ardupilot_log_reader-0.3.5.dist-info/METADATA
ardupilot_log_reader-0.3.5.dist-info/WHEEL
ardupilot_log_reader-0.3.5.dist-info/RECORD
