Metadata-Version: 2.3
Name: ardupilot_log_reader
Version: 0.3.5
Summary: module to read ardupilot binary logs to memory
Author-email: Thomas David <thomasdavid0@gmail.com>
Requires-Python: >=3.12
Requires-Dist: numpy>=2.1.3
Requires-Dist: pandas>=2.2.3
Requires-Dist: pymavlink>=2.4.42
